pyramid_okta/__init__.py
pyramid_okta/_version.py
pyramid_okta/request.py
pyramid_okta/session.py
pyramid_okta/settings.py
pyramid_okta/utils.py
pyramid_okta/security/__init__.py
pyramid_okta/security/authentication.py
pyramid_okta/security/authorization.py
pyramid_okta-2016.0.38.dist-info/DESCRIPTION.rst
pyramid_okta-2016.0.38.dist-info/METADATA
pyramid_okta-2016.0.38.dist-info/metadata.json
pyramid_okta-2016.0.38.dist-info/RECORD
pyramid_okta-2016.0.38.dist-info/top_level.txt
pyramid_okta-2016.0.38.dist-info/WHEEL
