Metadata-Version: 2.0
Name: pyramid-okta
Version: 2016.0.38
Summary: Bindings for the pyramid webframework and the Okta authorization system.
Home-page: https://github.com/bitesofcode/pyramid_okta
Author: Eric Hulser
Author-email: eric.hulser@gmail.com
License: MIT
Platform: UNKNOWN
Requires-Dist: pyramid
Requires-Dist: paste
Requires-Dist: okta
